{
  "dashboardStats": [
    {
      "id": 1,
      "icon": "FaMoneyBillAlt",
      "color": "#FF5733",
      "label": "Revenue",
      "percentage": "27",
      "value": "$28,684"
    },
    {
      "id": 2,
      "icon": "FaShoppingCart",
      "color": "green",
      "label": "Sales",
      "percentage": "-13",
      "value": "972"
    },
    {
      "id": 3,
      "icon": "FaDollarSign",
      "color": "#3357FF",
      "label": "Profit",
      "percentage": "58",
      "value": "$6410"
    },
    {
      "id": 4,
      "icon": "FaUsers",
      "color": "#F5A623",
      "label": "Users",
      "percentage": "44",
      "value": "17,591"
    }
  ],
  "products": [
    {
      "id": 1,
      "name": "Ledger",
      "price": "$50"
    },
    {
      "id": 2,
      "name": "T-shirt",
      "price": "$20"
    },
    {
      "id": 3,
      "name": "Cup",
      "price": "$16"
    },
    {
      "id": 2,
      "name": "Book",
      "price": "$45"
    },
    {
      "id": 2,
      "name": "Bot",
      "price": "$550"
    }
  ],
  "orders": [
    {
      "id": 1,
      "product": "Bot",
      "price": "$110",
      "order_date": "2024-09-16",
      "address": "Westlands, Suite 330",
      "status": "Shipped",
      "total_amount": "120",
      "shipping_fees": "10"
    },
    {
      "id": 2,
      "product": "Mug",
      "price": "$30",
      "order_date": "2024-09-16",
      "address": "Bamburi, Kisauni",
      "status": "Shipped",
      "total_amount": "20",
      "shipping_fees": "3"
    },
    {
      "id": 3,
      "product": "T-shirt",
      "price": "$30",
      "order_date": "2024-09-16",
      "address": "Langas, Eldoret",
      "status": "Shipped",
      "total_amount": "30",
      "shipping_fees": "3"
    },
    {
      "id": 4,
      "product": "Ledger",
      "price": "$30",
      "order_date": "2024-09-16",
      "address": "Kayole, Nakuru",
      "status": "Shipped",
      "total_amount": "250",
      "shipping_fees": "3"
    },
    {
      "id": 5,
      "product": "Bot",
      "price": "$30",
      "order_date": "2024-09-15",
      "address": "Nyali, Mombasa",
      "status": "Delivered",
      "total_amount": "120",
      "shipping_fees": "3"
    },
    {
      "id": 6,
      "product": "Ledger",
      "price": "$30",
      "order_date": "2024-09-15",
      "address": "Banana, Kiambu",
      "status": "Delivered",
      "total_amount": "250",
      "shipping_fees": "3"
    },
    {
      "id": 7,
      "product": "Ledger",
      "price": "$30",
      "order_date": "2024-09-15",
      "address": "Makongeni, Thika",
      "status": "Delivered",
      "total_amount": "250",
      "shipping_fees": "3"
    },
    {
      "id": 8,
      "product": "Bot",
      "price": "$30",
      "order_date": "2024-09-15",
      "address": "Thogoto, Nairobi",
      "status": "Delivered",
      "total_amount": "120",
      "shipping_fees": "3"
    },
    {
      "id": 9,
      "product": "Bot",
      "price": "$30",
      "order_date": "2024-09-15",
      "address": "Ruaka, Nairobi",
      "status": "Delivered",
      "total_amount": "120",
      "shipping_fees": "3"
    },
    {
      "id": 10,
      "product": "Ledger",
      "price": "$30",
      "order_date": "2024-09-15",
      "address": "Kibos, Kisumu",
      "status": "Delivered",
      "total_amount": "250",
      "shipping_fees": "3"
    }
  ],
  "ordersPerMonth": [
    { "month": "January", "orders_count": 120 },
    { "month": "February", "orders_count": 150 },
    { "month": "March", "orders_count": 180 },
    { "month": "April", "orders_count": 130 },
    { "month": "May", "orders_count": 170 },
    { "month": "June", "orders_count": 160 }
  ],
  "topProducts": [
    { "product_name": "Book", "num_orders": 50 },
    { "product_name": "Battlr Bot", "num_orders": 80 },
    { "product_name": "T-shirt", "num_orders": 65 },
    { "product_name": "Ledger", "num_orders": 90 }
  ],
  "productCategories": [
    { "category": "Electronics", "count": 30 },
    { "category": "Clothing", "count": 45 },
    { "category": "Food", "count": 20 },
    { "category": "Books", "count": 15 }
  ]    
  }
  